[
    { "total_amount": 1500000, "address": "Số 123, Đường ABC, Quận XYZ, Thành phố HCM", "phone_number": "0123456789", "createdAt": "2024-04-07T12:00:00Z", "code_oder": "A1B2C3D4E5" },
    { "total_amount": 2000000, "address": "Số 456, Đường XYZ, Quận ABC, Thành phố Hanoi", "phone_number": "0987654321", "createdAt": "2024-04-07T12:30:00Z", "code_oder": "F6G7H8I9J0" },
    { "total_amount": 1800000, "address": "Số 789, Đường MNO, Quận DEF, Thành phố Da Nang", "phone_number": "0321654987", "createdAt": "2024-04-07T13:00:00Z", "code_oder": "K1L2M3N4O5" },
    { "total_amount": 2200000, "address": "Số 321, Đường PQR, Quận LMN, Thành phố Can Tho", "phone_number": "0569321487", "createdAt": "2024-04-07T13:30:00Z", "code_oder": "P6Q7R8S9T0" },
    { "total_amount": 1300000, "address": "Số 654, Đường GHI, Quận STU, Thành phố Hai Phong", "phone_number": "0908765432", "createdAt": "2024-04-07T14:00:00Z", "code_oder": "U1V2W3X4Y5" },
    { "total_amount": 1900000, "address": "Số 987, Đường DEF, Quận QRS, Thành phố Vung Tau", "phone_number": "0975312468", "createdAt": "2024-04-07T14:30:00Z", "code_oder": "Z6A7B8C9D0" },
    { "total_amount": 1600000, "address": "Số 741, Đường JKL, Quận UVW, Thành phố Nha Trang", "phone_number": "0912345678", "createdAt": "2024-04-07T15:00:00Z", "code_oder": "E1F2G3H4I5" },
    { "total_amount": 2100000, "address": "Số 852, Đường RST, Quận XYZ, Thành phố Phan Thiet", "phone_number": "0389516724", "createdAt": "2024-04-07T15:30:00Z", "code_oder": "J6K7L8M9N0" },
    { "total_amount": 2400000, "address": "Số 369, Đường NOP, Quận EFG, Thành phố Hue", "phone_number": "0357924681", "createdAt": "2024-04-07T16:00:00Z", "code_oder": "O1P2Q3R4S5" },
    { "total_amount": 1700000, "address": "Số 258, Đường HIJ, Quận KLM, Thành phố Quy Nhon", "phone_number": "0946138275", "createdAt": "2024-04-07T16:30:00Z", "code_oder": "T6U7V8W9X0" },
    { "total_amount": 2300000, "address": "Số 147, Đường UVW, Quận NOP, Thành phố Vinh", "phone_number": "0392687451", "createdAt": "2024-04-07T17:00:00Z", "code_oder": "Y1Z2A3B4C5" },
    { "total_amount": 2000000, "address": "Số 369, Đường XYZ, Quận GHI, Thành phố Rach Gia", "phone_number": "0379852416", "createdAt": "2024-04-07T17:30:00Z", "code_oder": "D6E7F8G9H0" },
    { "total_amount": 1800000, "address": "Số 258, Đường EFG, Quận JKL, Thành phố Long Xuyen", "phone_number": "0918374652", "createdAt": "2024-04-07T18:00:00Z", "code_oder": "I1J2K3L4M5" },
    { "total_amount": 2500000, "address": "Số 741, Đường NOP, Quận UVW, Thành phố Cao Bang", "phone_number": "0389517246", "createdAt": "2024-04-07T18:30:00Z", "code_oder": "N6O7P8Q9R0" },
    { "total_amount": 2200000, "address": "Số 963, Đường ABC, Quận DEF, Thành phố Buon Ma Thuot", "phone_number": "0359264871", "createdAt": "2024-04-07T19:00:00Z", "code_oder": "S1T2U3V4W5" },
    { "total_amount": 1900000, "address": "Số 852, Đường LMN, Quận STU, Thành phố Soc Trang", "phone_number": "0946872513", "createdAt": "2024-04-07T19:30:00Z", "code_oder": "X6Y7Z8A9B0" },
    { "total_amount": 2700000, "address": "Số 159, Đường GHI, Quận QRS, Thành phố Tan An", "phone_number": "0935726148", "createdAt": "2024-04-07T20:00:00Z", "code_oder": "C1D2E3F4G5" },
    { "total_amount": 2000000, "address": "Số 456, Đường MNO, Quận HIJ, Thành phố Lao Cai", "phone_number": "0396821754", "createdAt": "2024-04-07T20:30:00Z", "code_oder": "H6I7J8K9L0" },
    { "total_amount": 2300000, "address": "Số 741, Đường PQR, Quận XYZ, Thành phố Thanh Hoa", "phone_number": "0321754869", "createdAt": "2024-04-07T21:00:00Z", "code_oder": "M1N2O3P4Q5" },
    { "total_amount": 2800000, "address": "Số 852, Đường STU, Quận MNO, Thành phố Ha Giang", "phone_number": "0389512764", "createdAt": "2024-04-07T21:30:00Z", "code_oder": "R6S7T8U9V0" }
  ]
  